swarming/__init__.py
swarming/version.py
swarming/core/__init__.py
swarming/core/particle.py
swarming/core/pso.py
swarming/utils/__init__.py
swarming/utils/argument_parser.py
swarming/utils/logger.py
swarming-1.0.0.dist-info/LICENSE
swarming-1.0.0.dist-info/METADATA
swarming-1.0.0.dist-info/WHEEL
swarming-1.0.0.dist-info/top_level.txt
swarming-1.0.0.dist-info/RECORD
