Metadata-Version: 2.1
Name: swarming
Version: 1.0.0
Summary: Swarming is a library that features both parallel and serial implementation of the PSO algorithm.
Home-page: https://github.com/giovcandido/swarming
Author: Giovani Candido
Author-email: giovcandido@outlook.com
License: GNU General Public License v3.0
Platform: UNKNOWN
Classifier: Development Status :: 5 - Production/Stable
Classifier: Programming Language :: Python :: 3.8
Classifier: Intended Audience :: Developers
Classifier: Intended Audience :: Education
Classifier: Intended Audience :: Science/Research
Classifier: Operating System :: OS Independent
Classifier: Natural Language :: English
Classifier: Topic :: Software Development :: Libraries
Classifier: Topic :: Software Development :: Libraries :: Python Modules
Classifier: License :: OSI Approved :: GNU General Public License v3 (GPLv3)
Requires-Python: >=3.8
License-File: LICENSE
Requires-Dist: ray[default]
Requires-Dist: numpy (>=1.21.2)
Requires-Dist: tqdm (>=4.62.3)
